MANIFEST.in
README.md
setup.py
TrackingProjectCFT/__init__.py
TrackingProjectCFT/command_line.py
TrackingProjectCFT/hostapd.py
TrackingProjectCFT/main.py
TrackingProjectCFT/monitor.py
TrackingProjectCFT/parse.py
TrackingProjectCFT.egg-info/PKG-INFO
TrackingProjectCFT.egg-info/SOURCES.txt
TrackingProjectCFT.egg-info/dependency_links.txt
TrackingProjectCFT.egg-info/entry_points.txt
TrackingProjectCFT.egg-info/not-zip-safe
TrackingProjectCFT.egg-info/requires.txt
TrackingProjectCFT.egg-info/top_level.txt