Metadata-Version: 1.1
Name: TrackingProjectCFT
Version: 0.1
Summary: TrackingProjectCFT
Home-page: https://bitbucket.org/MaceSteve/trackingprojectcft
Author: me
Author-email: me@mywebsite
License: UNKNOWN
Platform: UNKNOWN
Classifier: Development Status :: 3 - Alpha
